{
    "code": 200,
    "status": "OK",
    "data": {
        "timings": {
            "Fajr": "03:05",
            "Sunrise": "05:03",
            "Dhuhr": "13:07",
            "Asr": "17:23",
            "Sunset": "21:10",
            "Maghrib": "21:10",
            "Isha": "23:08",
            "Imsak": "02:55",
            "Midnight": "01:06",
            "Firstthird": "23:48",
            "Lastthird": "02:25"
        },
        "date": {
            "readable": "17 Jul 2007",
            "timestamp": "1184652000",
            "hijri": {
                "date": "02-07-1428",
                "format": "DD-MM-YYYY",
                "day": "02",
                "weekday": {
                    "en": "Al Thalaata",
                    "ar": "\u0627\u0644\u062b\u0644\u0627\u062b\u0627\u0621"
                },
                "month": {
                    "number": 7,
                    "en": "Rajab",
                    "ar": "\u0631\u064e\u062c\u064e\u0628"
                },
                "year": "1428",
                "designation": {
                    "abbreviated": "AH",
                    "expanded": "Anno Hegirae"
                },
                "holidays": []
            },
            "gregorian": {
                "date": "17-07-2007",
                "format": "DD-MM-YYYY",
                "day": "17",
                "weekday": {
                    "en": "Tuesday"
                },
                "month": {
                    "number": 7,
                    "en": "July"
                },
                "year": "2007",
                "designation": {
                    "abbreviated": "AD",
                    "expanded": "Anno Domini"
                }
            }
        },
        "meta": {
            "latitude": 51.508515,
            "longitude": -0.1254872,
            "timezone": "Europe\/London",
            "method": {
                "id": 2,
                "name": "Islamic Society of North America (ISNA)",
                "params": {
                    "Fajr": 15,
                    "Isha": 15
                },
                "location": {
                    "latitude": 39.70421229999999,
                    "longitude": -86.39943869999999
                }
            },
            "latitudeAdjustmentMethod": "ANGLE_BASED",
            "midnightMode": "STANDARD",
            "school": "STANDARD",
            "offset": {
                "Imsak": 0,
                "Fajr": 0,
                "Sunrise": 0,
                "Dhuhr": 0,
                "Asr": 0,
                "Maghrib": 0,
                "Sunset": 0,
                "Isha": 0,
                "Midnight": 0
            }
        }
    }
}